uploader/__init__.py
uploader/s3_mongo_helper.py
tattle_uploader-0.0.3.dist-info/METADATA
tattle_uploader-0.0.3.dist-info/WHEEL
tattle_uploader-0.0.3.dist-info/entry_points.txt
tattle_uploader-0.0.3.dist-info/top_level.txt
tattle_uploader-0.0.3.dist-info/RECORD
