Metadata-Version: 2.1
Name: tattle-uploader
Version: 0.0.3
Summary: Helper functions to assist tattle services in storing data
Home-page: https://github.com/tattle-made/
Author: kruttikanadig
Author-email: kruttika@tattle.co.in
License: GPL-3
Platform: UNKNOWN
Requires-Dist: boto3
Requires-Dist: pymongo
